[
  {
    "grid": [
      [
        11,
        4,
        11,
        1,
        1,
        1,
        5,
        4,
        11,
        11,
        1,
        11,
        11,
        11,
        11
      ],
      [
        11,
        11,
        11,
        11,
        1,
        11,
        5,
        11,
        11,
        1,
        1,
        1,
        1,
        11,
        11
      ],
      [
        4,
        11,
        11,
        11,
        11,
        4,
        4,
        5,
        1,
        4,
        1,
        1,
        1,
        11,
        11
      ],
      [
        11,
        11,
        11,
        11,
        11,
        4,
        11,
        5,
        5,
        1,
        4,
        1,
        1,
        11,
        11
      ],
      [
        11,
        11,
        4,
        11,
        11,
        11,
        4,
        4,
        11,
        11,
        11,
        1,
        1,
        1,
        11
      ],
      [
        11,
        4,
        11,
        4,
        11,
        1,
        1,
        11,
        5,
        11,
        11,
        4,
        1,
        11,
        11
      ],
      [
        1,
        4,
        4,
        11,
        1,
        1,
        1,
        1,
        5,
        11,
        4,
        11,
        4,
        11,
        11
      ],
      [
        1,
        4,
        11,
        1,
        1,
        1,
        1,
        1,
        4,
        11,
        11,
        11,
        11,
        11,
        11
      ],
      [
        11,
        11,
        4,
        11,
        4,
        1,
        1,
        5,
        11,
        11,
        11,
        4,
        4,
        11,
        4
      ],
      [
        11,
        11,
        4,
        4,
        11,
        1,
        11,
        11,
        11,
        4,
        11,
        11,
        11,
        11,
        11
      ],
      [
        11,
        4,
        11,
        4,
        4,
        11,
        11,
        5,
        1,
        1,
        11,
        4,
        11,
        11,
        11
      ],
      [
        11,
        11,
        11,
        11,
        11,
        4,
        11,
        4,
        3,
        11,
        4,
        4,
        11,
        1,
        1
      ],
      [
        11,
        11,
        11,
        11,
        11,
        11,
        11,
        11,
        11,
        4,
        4,
        4,
        11,
        1,
        1
      ],
      [
        11,
        11,
        11,
        11,
        11,
        4,
        11,
        11,
        11,
        11,
        3,
        2,
        4,
        4,
        11
      ],
      [
        10,
        10,
        10,
        10,
        10,
        10,
        10,
        10,
        10,
        10,
        10,
        10,
        10,
        10,
        10
      ]
    ],
    "settlements": [
      {
        "x": 20,
        "y": 35,
        "population": 1.778,
        "food": 0.579,
        "wealth": 0.005,
        "defense": 1.0,
        "has_port": false,
        "alive": true,
        "owner_id": 2
      },
      {
        "x": 23,
        "y": 38,
        "population": 2.326,
        "food": 0.781,
        "wealth": 0.032,
        "defense": 1.0,
        "has_port": true,
        "alive": true,
        "owner_id": 45
      },
      {
        "x": 24,
        "y": 29,
        "population": 1.974,
        "food": 0.186,
        "wealth": 0.032,
        "defense": 1.0,
        "has_port": false,
        "alive": true,
        "owner_id": 30
      },
      {
        "x": 12,
        "y": 32,
        "population": 1.736,
        "food": 0.789,
        "wealth": 0.01,
        "defense": 1.0,
        "has_port": false,
        "alive": true,
        "owner_id": 40
      },
      {
        "x": 18,
        "y": 32,
        "population": 1.806,
        "food": 0.324,
        "wealth": 0.004,
        "defense": 1.0,
        "has_port": false,
        "alive": true,
        "owner_id": 40
      },
      {
        "x": 17,
        "y": 30,
        "population": 1.574,
        "food": 0.595,
        "wealth": 0.003,
        "defense": 1.0,
        "has_port": false,
        "alive": true,
        "owner_id": 40
      },
      {
        "x": 26,
        "y": 36,
        "population": 1.099,
        "food": 0.695,
        "wealth": 0.002,
        "defense": 0.482,
        "has_port": false,
        "alive": true,
        "owner_id": 45
      },
      {
        "x": 16,
        "y": 32,
        "population": 1.534,
        "food": 0.599,
        "wealth": 0.0,
        "defense": 1.0,
        "has_port": false,
        "alive": true,
        "owner_id": 40
      },
      {
        "x": 17,
        "y": 25,
        "population": 1.746,
        "food": 0.582,
        "wealth": 0.01,
        "defense": 1.0,
        "has_port": false,
        "alive": true,
        "owner_id": 18
      },
      {
        "x": 24,
        "y": 26,
        "population": 1.957,
        "food": 0.697,
        "wealth": 0.01,
        "defense": 1.0,
        "has_port": false,
        "alive": true,
        "owner_id": 30
      },
      {
        "x": 23,
        "y": 28,
        "population": 2.01,
        "food": 0.612,
        "wealth": 0.008,
        "defense": 1.0,
        "has_port": false,
        "alive": true,
        "owner_id": 30
      },
      {
        "x": 25,
        "y": 36,
        "population": 1.22,
        "food": 0.883,
        "wealth": 0.001,
        "defense": 0.783,
        "has_port": false,
        "alive": true,
        "owner_id": 45
      },
      {
        "x": 16,
        "y": 26,
        "population": 1.486,
        "food": 0.858,
        "wealth": 0.02,
        "defense": 0.969,
        "has_port": false,
        "alive": true,
        "owner_id": 18
      },
      {
        "x": 17,
        "y": 33,
        "population": 1.673,
        "food": 0.833,
        "wealth": 0.009,
        "defense": 1.0,
        "has_port": false,
        "alive": true,
        "owner_id": 40
      },
      {
        "x": 19,
        "y": 31,
        "population": 1.673,
        "food": 0.6,
        "wealth": 0.01,
        "defense": 1.0,
        "has_port": false,
        "alive": true,
        "owner_id": 40
      },
      {
        "x": 23,
        "y": 26,
        "population": 1.445,
        "food": 0.828,
        "wealth": 0.008,
        "defense": 0.934,
        "has_port": false,
        "alive": true,
        "owner_id": 30
      },
      {
        "x": 15,
        "y": 25,
        "population": 1.018,
        "food": 0.903,
        "wealth": 0.016,
        "defense": 0.632,
        "has_port": false,
        "alive": true,
        "owner_id": 18
      },
      {
        "x": 16,
        "y": 31,
        "population": 1.096,
        "food": 0.895,
        "wealth": 0.001,
        "defense": 0.687,
        "has_port": false,
        "alive": true,
        "owner_id": 40
      },
      {
        "x": 18,
        "y": 31,
        "population": 0.831,
        "food": 0.92,
        "wealth": 0.001,
        "defense": 0.543,
        "has_port": false,
        "alive": true,
        "owner_id": 40
      },
      {
        "x": 17,
        "y": 31,
        "population": 1.005,
        "food": 0.862,
        "wealth": 0.001,
        "defense": 0.625,
        "has_port": false,
        "alive": true,
        "owner_id": 40
      },
      {
        "x": 22,
        "y": 27,
        "population": 1.029,
        "food": 0.902,
        "wealth": 0.001,
        "defense": 0.632,
        "has_port": false,
        "alive": true,
        "owner_id": 30
      },
      {
        "x": 22,
        "y": 25,
        "population": 1.227,
        "food": 0.883,
        "wealth": 0.006,
        "defense": 0.755,
        "has_port": false,
        "alive": true,
        "owner_id": 30
      },
      {
        "x": 21,
        "y": 28,
        "population": 0.659,
        "food": 0.937,
        "wealth": 0.002,
        "defense": 0.395,
        "has_port": false,
        "alive": true,
        "owner_id": 30
      },
      {
        "x": 23,
        "y": 27,
        "population": 0.827,
        "food": 0.907,
        "wealth": 0.007,
        "defense": 0.503,
        "has_port": false,
        "alive": true,
        "owner_id": 30
      },
      {
        "x": 23,
        "y": 29,
        "population": 1.008,
        "food": 0.904,
        "wealth": 0.011,
        "defense": 0.577,
        "has_port": false,
        "alive": true,
        "owner_id": 30
      },
      {
        "x": 21,
        "y": 26,
        "population": 0.84,
        "food": 0.92,
        "wealth": 0.005,
        "defense": 0.495,
        "has_port": false,
        "alive": true,
        "owner_id": 30
      },
      {
        "x": 20,
        "y": 27,
        "population": 0.84,
        "food": 0.92,
        "wealth": 0.006,
        "defense": 0.495,
        "has_port": false,
        "alive": true,
        "owner_id": 30
      },
      {
        "x": 22,
        "y": 26,
        "population": 0.4,
        "food": 0.393,
        "wealth": 0.001,
        "defense": 0.263,
        "has_port": false,
        "alive": true,
        "owner_id": 30
      },
      {
        "x": 18,
        "y": 33,
        "population": 0.388,
        "food": 0.649,
        "wealth": 0.001,
        "defense": 0.189,
        "has_port": false,
        "alive": true,
        "owner_id": 40
      },
      {
        "x": 24,
        "y": 27,
        "population": 0.613,
        "food": 0.644,
        "wealth": 0.003,
        "defense": 0.297,
        "has_port": false,
        "alive": true,
        "owner_id": 30
      },
      {
        "x": 24,
        "y": 28,
        "population": 0.602,
        "food": 0.716,
        "wealth": 0.003,
        "defense": 0.296,
        "has_port": false,
        "alive": true,
        "owner_id": 30
      },
      {
        "x": 16,
        "y": 25,
        "population": 0.5,
        "food": 0.196,
        "wealth": 0.002,
        "defense": 0.257,
        "has_port": false,
        "alive": true,
        "owner_id": 18
      },
      {
        "x": 17,
        "y": 34,
        "population": 0.479,
        "food": 0.742,
        "wealth": 0.002,
        "defense": 0.211,
        "has_port": false,
        "alive": true,
        "owner_id": 40
      },
      {
        "x": 19,
        "y": 32,
        "population": 0.478,
        "food": 0.658,
        "wealth": 0.002,
        "defense": 0.213,
        "has_port": false,
        "alive": true,
        "owner_id": 40
      },
      {
        "x": 26,
        "y": 37,
        "population": 0.425,
        "food": 0.557,
        "wealth": 0.0,
        "defense": 0.197,
        "has_port": false,
        "alive": true,
        "owner_id": 45
      },
      {
        "x": 24,
        "y": 30,
        "population": 0.533,
        "food": 0.765,
        "wealth": 0.008,
        "defense": 0.23,
        "has_port": false,
        "alive": true,
        "owner_id": 30
      },
      {
        "x": 12,
        "y": 31,
        "population": 0.448,
        "food": 0.616,
        "wealth": 0.002,
        "defense": 0.185,
        "has_port": false,
        "alive": true,
        "owner_id": 40
      },
      {
        "x": 21,
        "y": 35,
        "population": 0.5,
        "food": 0.407,
        "wealth": 0.002,
        "defense": 0.2,
        "has_port": false,
        "alive": true,
        "owner_id": 2
      },
      {
        "x": 17,
        "y": 32,
        "population": 0.5,
        "food": 0.122,
        "wealth": 0.001,
        "defense": 0.2,
        "has_port": false,
        "alive": true,
        "owner_id": 40
      },
      {
        "x": 18,
        "y": 30,
        "population": 0.5,
        "food": 0.207,
        "wealth": 0.001,
        "defense": 0.2,
        "has_port": false,
        "alive": true,
        "owner_id": 40
      },
      {
        "x": 15,
        "y": 32,
        "population": 0.5,
        "food": 0.207,
        "wealth": 0.0,
        "defense": 0.2,
        "has_port": false,
        "alive": true,
        "owner_id": 40
      },
      {
        "x": 25,
        "y": 37,
        "population": 0.4,
        "food": 0.156,
        "wealth": 0.003,
        "defense": 0.15,
        "has_port": false,
        "alive": true,
        "owner_id": 45
      },
      {
        "x": 25,
        "y": 29,
        "population": 0.4,
        "food": 0.037,
        "wealth": 0.003,
        "defense": 0.15,
        "has_port": false,
        "alive": true,
        "owner_id": 30
      }
    ],
    "viewport": {
      "x": 12,
      "y": 25,
      "w": 15,
      "h": 15
    },
    "width": 40,
    "height": 40,
    "queries_used": 23,
    "queries_max": 50
  }
]